easykubeflow/__init__.py
easykubeflow/utils.py
easykubeflow-0.0.10.dist-info/DESCRIPTION.rst
easykubeflow-0.0.10.dist-info/METADATA
easykubeflow-0.0.10.dist-info/RECORD
easykubeflow-0.0.10.dist-info/WHEEL
easykubeflow-0.0.10.dist-info/metadata.json
easykubeflow-0.0.10.dist-info/top_level.txt
