Metadata-Version: 2.0
Name: easykubeflow
Version: 0.0.10
Summary: High level of kubeflow SDK
Home-page: UNKNOWN
Author: Le Tuan Vu
Author-email: ltnv24@gmail.com
License: UNKNOWN
Platform: UNKNOWN
Classifier: Programming Language :: Python :: 3
Classifier: Operating System :: OS Independent
Requires-Python: >=3.6
Requires-Dist: kfp
